webEpy/__init__.py
webEpy/webEpy.py
webyPy/__init__.py
webyPy/webyPy.py
webyPy-0.0.2.dist-info/METADATA
webyPy-0.0.2.dist-info/RECORD
webyPy-0.0.2.dist-info/WHEEL
webyPy-0.0.2.dist-info/top_level.txt
