Metadata-Version: 2.1
Name: webyPy
Version: 0.0.2
Summary: A light-weight web-design package for Python.
Home-page: https://github.com/TakshanGowda/webEpy
Author: Takshan Gowda
Author-email: takshan.gowdii@gmail.com
License: UNKNOWN
Platform: UNKNOWN
Classifier: Programming Language :: Python :: 3
Classifier: License :: OSI Approved :: MIT License
Classifier: Operating System :: OS Independent
